metasub_utils.metagenscope-0.2.0-py3.6-nspkg.pth
metasub_utils/metagenscope/__init__.py
metasub_utils/metagenscope/cli.py
metasub_utils/metagenscope/constants.py
metasub_utils/metagenscope/metagenscope.py
metasub_utils/metagenscope/utils.py
metasub_utils.metagenscope-0.2.0.dist-info/METADATA
metasub_utils.metagenscope-0.2.0.dist-info/RECORD
metasub_utils.metagenscope-0.2.0.dist-info/WHEEL
metasub_utils.metagenscope-0.2.0.dist-info/namespace_packages.txt
metasub_utils.metagenscope-0.2.0.dist-info/top_level.txt
